Metadata-Version: 2.1
Name: zackdbtools
Version: 0.1.13
Summary: a python package to connect db and data sources like google sheets
Home-page: https://github.com/DaiZack/zackdbtools
Author: Zack Dai
Author-email: zack.dai@delta4digital.com
Classifier: Programming Language :: Python :: 3
Classifier: License :: OSI Approved :: MIT License
Classifier: Operating System :: OS Independent
